easyprojectstructure/__init__.py
easyprojectstructure/__main__.py
tests/__init__.py
tests/test_easyprojectstructure.py
easyprojectstructure-1.0.1.dist-info/LICENSE
easyprojectstructure-1.0.1.dist-info/METADATA
easyprojectstructure-1.0.1.dist-info/WHEEL
easyprojectstructure-1.0.1.dist-info/entry_points.txt
easyprojectstructure-1.0.1.dist-info/top_level.txt
easyprojectstructure-1.0.1.dist-info/RECORD
